{
  "fullimage": "girls/full/220_green_green",
  "fullmade": "",
  "fullmistress": "",
  "fullsecretary": "girls/full/secretary/green_green",
  "seed_ava": "content/pic/girls/face/220_sepia",
  "seed_ava_gray": "content/pic/girls/face/220_gray",
  "seed_ava_clear": "content/pic/girls/face/220",
  "seed_age": 0,
  "seed_boobs": 3,
  "seed_boobs_img": "boobs_DD",
  "seed_pussy_img": "pussy_g2",
  "seed_psy_basic": "",
  "seed_world": "",
  "bathing_alone": "girls/sceneF/bath_general",
  "cello": "girls/sceneF/cello_general",
  "cleaning": "girls/sceneF/clean_green",
  "cooking": "girls/sceneF/cook_general",
  "dance": "girls/sceneF/dance_general",
  "desertag": "girls/sceneF/dessertag_general",
  "enchanting": "girls/sceneF/enchanting_general",
  "fighting": "girls/sceneF/fight_general_girl",
  "flyte": "girls/sceneF/flute_green_elf_loli",
  "guitar": "girls/sceneF/guitar_general_girl",
  "gymnastics": "girls/sceneF/gym_general",
  "lesbo_bath": "girls/sceneF/lesbath_green_brown_mm",
  "nurse": "girls/sceneF/nurse_general",
  "piano": "girls/sceneF/piano_green_long_greeneye",
  "rest": "girls/sceneF/rest_green_long",
  "secretary": "girls/sceneF/secretary_general",
  "student": "girls/sceneF/study_green",
  "singing": "girls/full/220_green_green",
  "violin": "girls/sceneF/violin_green_greeneye",
  "washing": "girls/sceneF/wash_general",
  "analfisting": "girls/sexF/analfisting_general_girl",
  "analsex": "girls/sexF/analsex_general",
  "bondage": "girls/sexF/bdsm_green_blueye_milf",
  "bdsm": "girls/sexF/bdsm_green_milf",
  "bj": "girls/sexF/bj_green_greeneye",
  "bukake": "girls/sexF/buakake_general",
  "disgrace": "girls/sexF/exhibit_general_girl",
  "defloration": "girls/sexF/defloration_green_darkeye",
  "deprivation_suit": "girls/sexF/dsuit_general",
  "dog_sex": "girls/sexF/dog_green_greeneye",
  "dildo": "girls/sexF/dildo_general",
  "dt": "girls/sexF/bj_green_greeneye",
  "enema": "girls/sexF/enema_green_long_brown",
  "exhibit": "girls/sexF/exhibit_general_girl",
  "fisting": "girls/sexF/fisting_general",
  "fj": "girls/sexF/fj_general_girl",
  "gangbang": "girls/sexF/gangbang_general_girl",
  "hj": "girls/sexF/hj_green_greeneye",
  "horse_sex": "girls/sexF/horse_general_2",
  "hug": "girls/full/220_green_green",
  "kiss": "girls/sexF/kiss_general",
  "kopro": "girls/sexF/oralfetish_green_long",
  "kuni": "girls/sexF/exhibit_general_girl",
  "lesbian": "girls/sexF/lesbo_greenlonggoldeye_gg",
  "masturbation": "girls/sexF/masturbation_general",
  "pazuri": "girls/sexF/pazuri_general",
  "petplay": "girls/sexF/petplay_black_long_blackeye",
  "petting": "girls/sexF/petting_general_girl_3",
  "pig_sex": "girls/sexF/pig_general_girl",
  "ponyplay": "girls/sexF/ponyplay_general",
  "rimming": "girls/sexF/rimming_general",
  "seduce": "girls/sexF/exhibit_general_girl",
  "sex_vaginal": "girls/sexF/sex_green_long_browneye",
  "spider": "girls/sexF/spider_general_milf",
  "thongue": "girls/sexF/oral_general",
  "tentacles": "girls/sexF/tentacle_general_girl",
  "urine_drink": "girls/sexF/urine_general",
  "branding": "girls/tortureF/branding_general_2",
  "cane": "girls/tortureF/cane_general_2",
  "ear_grab": "girls/tortureF/force_general",
  "ironmaiden": "girls/tortureF/ironmaiden_general_girl",
  "fireswing": "girls/tortureF/fireswing_general_2",
  "fist_hit": "girls/tortureF/hit_general",
  "leash": "girls/tortureF/whip_general",
  "needle": "girls/tortureF/needle_general_girl",
  "pins": "girls/tortureF/pins_general_girl",
  "slap": "girls/tortureF/slap_general",
  "spank": "girls/tortureF/spank_general",
  "strappado": "girls/tortureF/strappado_general",
  "verminpit": "girls/tortureF/verminpit_general",
  "water": "girls/tortureF/water_general",
  "wax": "girls/tortureF/wax_general",
  "woodenhorse": "girls/tortureF/woodenhorse_green_darkeye",
  "whip": "girls/tortureF/whip_general",
  "impaling": "girls/tortureF/impaling_general",
  "decapitation": "girls/tortureF/decapitation_general",
  "hanging": "girls/tortureF/hanging_general",
  "throat_slit": "girls/tortureF/decapitation_general",
  "cook_whole": "girls/tortureF/cooked_general"
}
