{
  "seed_name": "Вильгельмина",
  "seed_callisthenics": 2,
  "seed_vocal": 2,
  "seed_expression": 2,
  "seed_beauty": 5,
  "seed_stamina": 2,
  "seed_sensitivity": 5,
  "seed_temper": 5,
  "seed_ego": 5,
  "seed_pride": 3,
  "seed_intellect": 3,
  "seed_exotic": 1,
  "seed_fat": 0,
  "seed_spoil": 3,
  "stock_world_description": "   В моем мире Светлый Альянс ведет нескончаемую войну с Древним Злом. В альянс входят все достойные народы: и светлые эльфы, и гномы и цивилизованные люди. Даже ангелы и единороги бьются на нашей стороне, но у Врага есть драконы и тролли. Он хочет поработить всех, чтобы в мире воцарилась Тьма.",
  "stock_family_description": "   Мой папа - король Артурии. Артурия - очень гордое королевство с большой военной историей, хотя земель у нас и немного. Наши паладины известны по всему миру своим благородством и вселяют ужас в жалких прихвостней Врага одним своим видом. А еще у меня был ручной единорог. Эх, если бы он был тут...",
  "seed_metabolism": 1,
  "seed_virginity": 0,
  "seed_nymphomania": -1,
  "seed_nymphomania_revealed": 2,
  "seed_masohism": -1,
  "seed_abuse_attitude": -1,
  "seed_blood_attitude": -1,
  "seed_passion_sweets": 1,
  "seed_passion_fame": 1,
  "seed_passion_comfort": 1,
  "fullimage": "girls/full/025_pink_long_red",
  "fullmade": "girls/full/maid/25_maid",
  "fullmistress": "girls/full/mistress/25_mistress",
  "fullsecretary": "girls/full/secretary/25_secretary",
  "seed_ava": "content/pic/girls/face/025_sepia",
  "seed_ava_gray": "content/pic/girls/face/025_gray",
  "seed_ava_clear": "content/pic/girls/face/025",
  "seed_age": 1,
  "seed_boobs": 1,
  "seed_boobs_img": "boobs_BB",
  "seed_pussy_img": "pussy_l3",
  "seed_psy_basic": "arrogant",
  "seed_world": "",
  "bathing_alone": "girls/scene/bath_25",
  "cello": "girls/scene/cello_general_loli",
  "cleaning": "girls/scene/clean_red_darkeye",
  "cooking": "girls/scene/cook_pink_blueeye",
  "dance": "girls/scene/dance_general",
  "desertag": "girls/scene/dessertag_general_loli",
  "enchanting": "girls/scene/enchanting_general",
  "fighting": "girls/scene/fight_red_darkeye",
  "flyte": "girls/scene/flute_pink_short_blueye_loli",
  "guitar": "girls/scene/guitar_pink_long",
  "gymnastics": "girls/scene/gym_pink_blueeye_loli",
  "lesbo_bath": "girls/scene/lesbath_black_pinklong_ml",
  "nurse": "girls/scene/nurse_general",
  "piano": "girls/scene/piano_general_loli",
  "rest": "girls/scene/rest_25",
  "secretary": "girls/scene/secretary_general",
  "student": "girls/scene/study_red_darkeye",
  "singing": "girls/full/025_pink_long_red",
  "violin": "girls/scene/violin_general_loli",
  "washing": "girls/scene/wash_pink_loli",
  "analfisting": "girls/sex/analfisting_general",
  "analsex": "girls/sex/analsex_pink_loli",
  "bondage": "girls/sex/bdsm_pink_loli",
  "bdsm": "girls/sex/bdsm_pink_loli",
  "bj": "girls/sex/bj_pink_loli",
  "bukake": "girls/sex/buakake_25",
  "disgrace": "girls/sex/disgrace_25",
  "defloration": "girls/sex/defloration_25",
  "deprivation_suit": "girls/sex/dsuit_general_loli",
  "dog_sex": "girls/sex/dog_pink_long_redeye_loli",
  "dildo": "girls/sex/dildo_general",
  "dt": "girls/sex/dt_red_short_redeye",
  "enema": "girls/sex/enema_general_loli",
  "exhibit": "girls/sex/exhibit_25",
  "fisting": "girls/sex/fisting_general",
  "fj": "girls/sex/fj_25",
  "gangbang": "girls/sex/gangbang_ping_redeye_loli",
  "hj": "girls/sex/hj_brown_browneye_loli",
  "horse_sex": "girls/sex/horse_general_loli",
  "hug": "girls/sex/hug_25",
  "kiss": "girls/sex/kiss_general",
  "kopro": "girls/sex/oralfetish_red",
  "kuni": "girls/sex/kuni_25",
  "lesbian": "girls/sex/lesbo_pinkshortredeye_blondlong_ll",
  "masturbation": "girls/sex/masturbation_25",
  "pazuri": "girls/sex/pazuri_general_loli",
  "petplay": "girls/sex/petplay_25",
  "petting": "girls/sex/petting_pink_blueeye",
  "pig_sex": "girls/sex/pig_general_loli",
  "ponyplay": "girls/sex/ponyplay_general_loli",
  "rimming": "girls/sex/rimming_pink_blueeye",
  "seduce": "girls/sex/seduce_25",
  "sex_vaginal": "girls/sex/sex_25",
  "spider": "girls/sex/spider_general_loli",
  "thongue": "girls/sex/oral_general_loli",
  "tentacles": "girls/sex/tentacle_25",
  "urine_drink": "girls/sex/urine_red_darkeye_loli",
  "branding": "girls/torture/branding_general_loli",
  "cane": "girls/torture/cane_general",
  "ear_grab": "girls/torture/force_loli",
  "ironmaiden": "girls/torture/ironmaiden_general",
  "fireswing": "girls/torture/fireswing_general",
  "fist_hit": "girls/torture/hit_general",
  "leash": "girls/torture/cane_general",
  "needle": "girls/torture/needle_general_loli",
  "pins": "girls/torture/pins_general_loli",
  "slap": "girls/torture/slap_general",
  "spank": "girls/torture/spank_pink",
  "strappado": "girls/torture/strappado_general",
  "verminpit": "girls/torture/verminpit_general",
  "water": "girls/torture/water_general",
  "wax": "girls/torture/wax_pink_short_loli",
  "woodenhorse": "girls/torture/woodenhorse_general",
  "whip": "girls/torture/cane_general",
  "impaling": "girls/torture/impaling_general_loli",
  "decapitation": "girls/torture/decapitation_general_loli",
  "hanging": "girls/torture/hanging_general",
  "throat_slit": "girls/torture/decapitation_general_loli",
  "cook_whole": "girls/torture/cooked_general_loli"
}